mandre_inapp/__init__.py
mandreinapp-1.0.0.dist-info/METADATA
mandreinapp-1.0.0.dist-info/WHEEL
mandreinapp-1.0.0.dist-info/top_level.txt
mandreinapp-1.0.0.dist-info/RECORD
