Metadata-Version: 2.4
Name: MandreInApp
Version: 1.0.0
Summary: Simple In-App Notification library for MandreLib based plugins. Original by @meeowPlugins.
Author: @meeowPlugins (Ported for MandreLib)
Classifier: Programming Language :: Python :: 3
Classifier: License :: OSI Approved :: MIT License
Classifier: Operating System :: Android
Requires-Python: >=3.6
Dynamic: author
Dynamic: classifier
Dynamic: description
Dynamic: description-content-type
Dynamic: requires-python
Dynamic: summary
